{"external_urls":{"spotify":"https:\/\/open.spotify.com\/playlist\/33yLOStnp2emkEA76ew1Dz"},"id":"33yLOStnp2emkEA76ew1Dz","description":"","tracks":{"total":15,"items":[{"added_at":"2020-09-11T09:28:15Z","added_by":{"id":"petervschorn","external_urls":{"spotify":"https:\/\/open.spotify.com\/user\/petervschorn"},"href":"https:\/\/api.spotify.com\/v1\/users\/petervschorn","uri":"spotify:user:petervschorn","type":"user"},"is_local":false,"track":{"id":"4HDLmWf73mge8isanCASnU","name":"Part III","album":{"images":[{"width":640,"url":"https:\/\/i.scdn.co\/image\/ab67616d0000b2739d45a127005f8a96652280bd","height":640},{"width":300,"url":"https:\/\/i.scdn.co\/image\/ab67616d00001e029d45a127005f8a96652280bd","height":300},{"width":64,"url":"https:\/\/i.scdn.co\/image\/ab67616d000048519d45a127005f8a96652280bd","height":64}],"release_date_precision":"day","release_date":"2019-06-14","id":"3vukTUpiENDHDoYTVrwqtz","uri":"spotify:album:3vukTUpiENDHDoYTVrwqtz","external_urls":{"spotify":"https:\/\/open.spotify.com\/album\/3vukTUpiENDHDoYTVrwqtz"},"href":"https:\/\/api.spotify.com\/v1\/albums\/3vukTUpiENDHDoYTVrwqtz","available_markets":["AD","AE","AL","AR","AT","AU","BA","BE","BG","BH","BO","BR","BY","CA","CH","CL","CO","CR","CY","CZ","DE","DK","DO","DZ","EC","EE","EG","ES","FI","FR","GB","GR","GT","HK","HN","HR","HU","ID","IE","IL","IN","IS","IT","JO","JP","KW","KZ","LB","LI","LT","LU","LV","MA","MC","MD","ME","MK","MT","MX","MY","NI","NL","NO","NZ","OM","PA","PE","PH","PL","PS","PT","PY","QA","RO","RS","RU","SA","SE","SG","SI","SK","SV","TH","TN","TR","TW","UA","US","UY","VN","XK","ZA"],"type":"album","name":"Jinx","artists":[{"type":"artist","id":"4kSGbjWGxTchKpIxXPJv0B","external_urls":{"spotify":"https:\/\/open.spotify.com\/artist\/4kSGbjWGxTchKpIxXPJv0B"},"name":"Crumb","uri":"spotify:artist:4kSGbjWGxTchKpIxXPJv0B","href":"https:\/\/api.spotify.com\/v1\/artists\/4kSGbjWGxTchKpIxXPJv0B"}]},"disc_number":1,"uri":"spotify:track:4HDLmWf73mge8isanCASnU","artists":[{"type":"artist","id":"4kSGbjWGxTchKpIxXPJv0B","external_urls":{"spotify":"https:\/\/open.spotify.com\/artist\/4kSGbjWGxTchKpIxXPJv0B"},"name":"Crumb","uri":"spotify:artist:4kSGbjWGxTchKpIxXPJv0B","href":"https:\/\/api.spotify.com\/v1\/artists\/4kSGbjWGxTchKpIxXPJv0B"}],"href":"https:\/\/api.spotify.com\/v1\/tracks\/4HDLmWf73mge8isanCASnU","is_local":false,"popularity":56,"available_markets":["AD","AE","AL","AR","AT","AU","BA","BE","BG","BH","BO","BR","BY","CA","CH","CL","CO","CR","CY","CZ","DE","DK","DO","DZ","EC","EE","EG","ES","FI","FR","GB","GR","GT","HK","HN","HR","HU","ID","IE","IL","IN","IS","IT","JO","JP","KW","KZ","LB","LI","LT","LU","LV","MA","MC","MD","ME","MK","MT","MX","MY","NI","NL","NO","NZ","OM","PA","PE","PH","PL","PS","PT","PY","QA","RO","RS","RU","SA","SE","SG","SI","SK","SV","TH","TN","TR","TW","UA","US","UY","VN","XK","ZA"],"type":"track","explicit":false,"duration_ms":222920,"external_urls":{"spotify":"https:\/\/open.spotify.com\/track\/4HDLmWf73mge8isanCASnU"},"external_ids":{"isrc":"TCAEC1957424"}}},{"added_at":"2020-01-04T11:02:06Z","added_by":{"id":"petervschorn","external_urls":{"spotify":"https:\/\/open.spotify.com\/user\/petervschorn"},"href":"https:\/\/api.spotify.com\/v1\/users\/petervschorn","uri":"spotify:user:petervschorn","type":"user"},"is_local":false,"track":{"id":"2cOzI3LOIkRIKEidcGZ1Bc","name":"Plants","album":{"images":[{"width":640,"url":"https:\/\/i.scdn.co\/image\/ab67616d0000b2736147b24815415ae922d2a88f","height":640},{"width":300,"url":"https:\/\/i.scdn.co\/image\/ab67616d00001e026147b24815415ae922d2a88f","height":300},{"width":64,"url":"https:\/\/i.scdn.co\/image\/ab67616d000048516147b24815415ae922d2a88f","height":64}],"release_date_precision":"day","release_date":"2017-06-23","id":"2Q61Zm3rOli876QegmVY50","uri":"spotify:album:2Q61Zm3rOli876QegmVY50","external_urls":{"spotify":"https:\/\/open.spotify.com\/album\/2Q61Zm3rOli876QegmVY50"},"href":"https:\/\/api.spotify.com\/v1\/albums\/2Q61Zm3rOli876QegmVY50","available_markets":["AD","AE","AL","AR","AT","AU","BA","BE","BG","BH","BO","BR","BY","CA","CH","CL","CO","CR","CY","CZ","DE","DK","DO","DZ","EC","EE","EG","ES","FI","FR","GB","GR","GT","HK","HN","HR","HU","ID","IE","IL","IN","IS","IT","JO","JP","KW","KZ","LB","LI","LT","LU","LV","MA","MC","MD","ME","MK","MT","MX","MY","NI","NL","NO","NZ","OM","PA","PE","PH","PL","PS","PT","PY","QA","RO","RS","RU","SA","SE","SG","SI","SK","SV","TH","TN","TR","TW","UA","US","UY","VN","XK","ZA"],"type":"album","name":"Locket","artists":[{"type":"artist","id":"4kSGbjWGxTchKpIxXPJv0B","external_urls":{"spotify":"https:\/\/open.spotify.com\/artist\/4kSGbjWGxTchKpIxXPJv0B"},"name":"Crumb","uri":"spotify:artist:4kSGbjWGxTchKpIxXPJv0B","href":"https:\/\/api.spotify.com\/v1\/artists\/4kSGbjWGxTchKpIxXPJv0B"}]},"disc_number":1,"uri":"spotify:track:2cOzI3LOIkRIKEidcGZ1Bc","artists":[{"type":"artist","id":"4kSGbjWGxTchKpIxXPJv0B","external_urls":{"spotify":"https:\/\/open.spotify.com\/artist\/4kSGbjWGxTchKpIxXPJv0B"},"name":"Crumb","uri":"spotify:artist:4kSGbjWGxTchKpIxXPJv0B","href":"https:\/\/api.spotify.com\/v1\/artists\/4kSGbjWGxTchKpIxXPJv0B"}],"href":"https:\/\/api.spotify.com\/v1\/tracks\/2cOzI3LOIkRIKEidcGZ1Bc","is_local":false,"popularity":61,"available_markets":["AD","AE","AL","AR","AT","AU","BA","BE","BG","BH","BO","BR","BY","CA","CH","CL","CO","CR","CY","CZ","DE","DK","DO","DZ","EC","EE","EG","ES","FI","FR","GB","GR","GT","HK","HN","HR","HU","ID","IE","IL","IN","IS","IT","JO","JP","KW","KZ","LB","LI","LT","LU","LV","MA","MC","MD","ME","MK","MT","MX","MY","NI","NL","NO","NZ","OM","PA","PE","PH","PL","PS","PT","PY","QA","RO","RS","RU","SA","SE","SG","SI","SK","SV","TH","TN","TR","TW","UA","US","UY","VN","XK","ZA"],"type":"track","explicit":false,"duration_ms":191904,"external_urls":{"spotify":"https:\/\/open.spotify.com\/track\/2cOzI3LOIkRIKEidcGZ1Bc"},"external_ids":{"isrc":"TCADB1785722"}}},{"added_at":"2020-01-04T11:02:18Z","added_by":{"id":"petervschorn","external_urls":{"spotify":"https:\/\/open.spotify.com\/user\/petervschorn"},"href":"https:\/\/api.spotify.com\/v1\/users\/petervschorn","uri":"spotify:user:petervschorn","type":"user"},"is_local":false,"track":{"id":"0bxcUgWlOURkU6lZt4zog0","name":"Locket","album":{"images":[{"width":640,"url":"https:\/\/i.scdn.co\/image\/ab67616d0000b2736147b24815415ae922d2a88f","height":640},{"width":300,"url":"https:\/\/i.scdn.co\/image\/ab67616d00001e026147b24815415ae922d2a88f","height":300},{"width":64,"url":"https:\/\/i.scdn.co\/image\/ab67616d000048516147b24815415ae922d2a88f","height":64}],"release_date_precision":"day","release_date":"2017-06-23","id":"2Q61Zm3rOli876QegmVY50","uri":"spotify:album:2Q61Zm3rOli876QegmVY50","external_urls":{"spotify":"https:\/\/open.spotify.com\/album\/2Q61Zm3rOli876QegmVY50"},"href":"https:\/\/api.spotify.com\/v1\/albums\/2Q61Zm3rOli876QegmVY50","available_markets":["AD","AE","AL","AR","AT","AU","BA","BE","BG","BH","BO","BR","BY","CA","CH","CL","CO","CR","CY","CZ","DE","DK","DO","DZ","EC","EE","EG","ES","FI","FR","GB","GR","GT","HK","HN","HR","HU","ID","IE","IL","IN","IS","IT","JO","JP","KW","KZ","LB","LI","LT","LU","LV","MA","MC","MD","ME","MK","MT","MX","MY","NI","NL","NO","NZ","OM","PA","PE","PH","PL","PS","PT","PY","QA","RO","RS","RU","SA","SE","SG","SI","SK","SV","TH","TN","TR","TW","UA","US","UY","VN","XK","ZA"],"type":"album","name":"Locket","artists":[{"type":"artist","id":"4kSGbjWGxTchKpIxXPJv0B","external_urls":{"spotify":"https:\/\/open.spotify.com\/artist\/4kSGbjWGxTchKpIxXPJv0B"},"name":"Crumb","uri":"spotify:artist:4kSGbjWGxTchKpIxXPJv0B","href":"https:\/\/api.spotify.com\/v1\/artists\/4kSGbjWGxTchKpIxXPJv0B"}]},"disc_number":1,"uri":"spotify:track:0bxcUgWlOURkU6lZt4zog0","artists":[{"type":"artist","id":"4kSGbjWGxTchKpIxXPJv0B","external_urls":{"spotify":"https:\/\/open.spotify.com\/artist\/4kSGbjWGxTchKpIxXPJv0B"},"name":"Crumb","uri":"spotify:artist:4kSGbjWGxTchKpIxXPJv0B","href":"https:\/\/api.spotify.com\/v1\/artists\/4kSGbjWGxTchKpIxXPJv0B"}],"href":"https:\/\/api.spotify.com\/v1\/tracks\/0bxcUgWlOURkU6lZt4zog0","is_local":false,"popularity":69,"available_markets":["AD","AE","AL","AR","AT","AU","BA","BE","BG","BH","BO","BR","BY","CA","CH","CL","CO","CR","CY","CZ","DE","DK","DO","DZ","EC","EE","EG","ES","FI","FR","GB","GR","GT","HK","HN","HR","HU","ID","IE","IL","IN","IS","IT","JO","JP","KW","KZ","LB","LI","LT","LU","LV","MA","MC","MD","ME","MK","MT","MX","MY","NI","NL","NO","NZ","OM","PA","PE","PH","PL","PS","PT","PY","QA","RO","RS","RU","SA","SE","SG","SI","SK","SV","TH","TN","TR","TW","UA","US","UY","VN","XK","ZA"],"type":"track","explicit":false,"duration_ms":318378,"external_urls":{"spotify":"https:\/\/open.spotify.com\/track\/0bxcUgWlOURkU6lZt4zog0"},"external_ids":{"isrc":"TCADC1793184"}}},{"added_at":"2020-01-04T11:12:28Z","added_by":{"id":"petervschorn","external_urls":{"spotify":"https:\/\/open.spotify.com\/user\/petervschorn"},"href":"https:\/\/api.spotify.com\/v1\/users\/petervschorn","uri":"spotify:user:petervschorn","type":"user"},"is_local":false,"track":{"id":"6pMNKv4Ad6gSsoKGA4fkct","name":"Nina","album":{"images":[{"width":640,"url":"https:\/\/i.scdn.co\/image\/ab67616d0000b2739d45a127005f8a96652280bd","height":640},{"width":300,"url":"https:\/\/i.scdn.co\/image\/ab67616d00001e029d45a127005f8a96652280bd","height":300},{"width":64,"url":"https:\/\/i.scdn.co\/image\/ab67616d000048519d45a127005f8a96652280bd","height":64}],"release_date_precision":"day","release_date":"2019-06-14","id":"3vukTUpiENDHDoYTVrwqtz","uri":"spotify:album:3vukTUpiENDHDoYTVrwqtz","external_urls":{"spotify":"https:\/\/open.spotify.com\/album\/3vukTUpiENDHDoYTVrwqtz"},"href":"https:\/\/api.spotify.com\/v1\/albums\/3vukTUpiENDHDoYTVrwqtz","available_markets":["AD","AE","AL","AR","AT","AU","BA","BE","BG","BH","BO","BR","BY","CA","CH","CL","CO","CR","CY","CZ","DE","DK","DO","DZ","EC","EE","EG","ES","FI","FR","GB","GR","GT","HK","HN","HR","HU","ID","IE","IL","IN","IS","IT","JO","JP","KW","KZ","LB","LI","LT","LU","LV","MA","MC","MD","ME","MK","MT","MX","MY","NI","NL","NO","NZ","OM","PA","PE","PH","PL","PS","PT","PY","QA","RO","RS","RU","SA","SE","SG","SI","SK","SV","TH","TN","TR","TW","UA","US","UY","VN","XK","ZA"],"type":"album","name":"Jinx","artists":[{"type":"artist","id":"4kSGbjWGxTchKpIxXPJv0B","external_urls":{"spotify":"https:\/\/open.spotify.com\/artist\/4kSGbjWGxTchKpIxXPJv0B"},"name":"Crumb","uri":"spotify:artist:4kSGbjWGxTchKpIxXPJv0B","href":"https:\/\/api.spotify.com\/v1\/artists\/4kSGbjWGxTchKpIxXPJv0B"}]},"disc_number":1,"uri":"spotify:track:6pMNKv4Ad6gSsoKGA4fkct","artists":[{"type":"artist","id":"4kSGbjWGxTchKpIxXPJv0B","external_urls":{"spotify":"https:\/\/open.spotify.com\/artist\/4kSGbjWGxTchKpIxXPJv0B"},"name":"Crumb","uri":"spotify:artist:4kSGbjWGxTchKpIxXPJv0B","href":"https:\/\/api.spotify.com\/v1\/artists\/4kSGbjWGxTchKpIxXPJv0B"}],"href":"https:\/\/api.spotify.com\/v1\/tracks\/6pMNKv4Ad6gSsoKGA4fkct","is_local":false,"popularity":53,"available_markets":["AD","AE","AL","AR","AT","AU","BA","BE","BG","BH","BO","BR","BY","CA","CH","CL","CO","CR","CY","CZ","DE","DK","DO","DZ","EC","EE","EG","ES","FI","FR","GB","GR","GT","HK","HN","HR","HU","ID","IE","IL","IN","IS","IT","JO","JP","KW","KZ","LB","LI","LT","LU","LV","MA","MC","MD","ME","MK","MT","MX","MY","NI","NL","NO","NZ","OM","PA","PE","PH","PL","PS","PT","PY","QA","RO","RS","RU","SA","SE","SG","SI","SK","SV","TH","TN","TR","TW","UA","US","UY","VN","XK","ZA"],"type":"track","explicit":false,"duration_ms":200280,"external_urls":{"spotify":"https:\/\/open.spotify.com\/track\/6pMNKv4Ad6gSsoKGA4fkct"},"external_ids":{"isrc":"QMB621900202"}}},{"added_at":"2020-01-04T11:47:25Z","added_by":{"id":"petervschorn","external_urls":{"spotify":"https:\/\/open.spotify.com\/user\/petervschorn"},"href":"https:\/\/api.spotify.com\/v1\/users\/petervschorn","uri":"spotify:user:petervschorn","type":"user"},"is_local":false,"track":{"id":"7qAy6TR1MrSeUV8OpMlNS1","name":"Jinx","album":{"images":[{"width":640,"url":"https:\/\/i.scdn.co\/image\/ab67616d0000b2739d45a127005f8a96652280bd","height":640},{"width":300,"url":"https:\/\/i.scdn.co\/image\/ab67616d00001e029d45a127005f8a96652280bd","height":300},{"width":64,"url":"https:\/\/i.scdn.co\/image\/ab67616d000048519d45a127005f8a96652280bd","height":64}],"release_date_precision":"day","release_date":"2019-06-14","id":"3vukTUpiENDHDoYTVrwqtz","uri":"spotify:album:3vukTUpiENDHDoYTVrwqtz","external_urls":{"spotify":"https:\/\/open.spotify.com\/album\/3vukTUpiENDHDoYTVrwqtz"},"href":"https:\/\/api.spotify.com\/v1\/albums\/3vukTUpiENDHDoYTVrwqtz","available_markets":["AD","AE","AL","AR","AT","AU","BA","BE","BG","BH","BO","BR","BY","CA","CH","CL","CO","CR","CY","CZ","DE","DK","DO","DZ","EC","EE","EG","ES","FI","FR","GB","GR","GT","HK","HN","HR","HU","ID","IE","IL","IN","IS","IT","JO","JP","KW","KZ","LB","LI","LT","LU","LV","MA","MC","MD","ME","MK","MT","MX","MY","NI","NL","NO","NZ","OM","PA","PE","PH","PL","PS","PT","PY","QA","RO","RS","RU","SA","SE","SG","SI","SK","SV","TH","TN","TR","TW","UA","US","UY","VN","XK","ZA"],"type":"album","name":"Jinx","artists":[{"type":"artist","id":"4kSGbjWGxTchKpIxXPJv0B","external_urls":{"spotify":"https:\/\/open.spotify.com\/artist\/4kSGbjWGxTchKpIxXPJv0B"},"name":"Crumb","uri":"spotify:artist:4kSGbjWGxTchKpIxXPJv0B","href":"https:\/\/api.spotify.com\/v1\/artists\/4kSGbjWGxTchKpIxXPJv0B"}]},"disc_number":1,"uri":"spotify:track:7qAy6TR1MrSeUV8OpMlNS1","artists":[{"type":"artist","id":"4kSGbjWGxTchKpIxXPJv0B","external_urls":{"spotify":"https:\/\/open.spotify.com\/artist\/4kSGbjWGxTchKpIxXPJv0B"},"name":"Crumb","uri":"spotify:artist:4kSGbjWGxTchKpIxXPJv0B","href":"https:\/\/api.spotify.com\/v1\/artists\/4kSGbjWGxTchKpIxXPJv0B"}],"href":"https:\/\/api.spotify.com\/v1\/tracks\/7qAy6TR1MrSeUV8OpMlNS1","is_local":false,"popularity":46,"available_markets":["AD","AE","AL","AR","AT","AU","BA","BE","BG","BH","BO","BR","BY","CA","CH","CL","CO","CR","CY","CZ","DE","DK","DO","DZ","EC","EE","EG","ES","FI","FR","GB","GR","GT","HK","HN","HR","HU","ID","IE","IL","IN","IS","IT","JO","JP","KW","KZ","LB","LI","LT","LU","LV","MA","MC","MD","ME","MK","MT","MX","MY","NI","NL","NO","NZ","OM","PA","PE","PH","PL","PS","PT","PY","QA","RO","RS","RU","SA","SE","SG","SI","SK","SV","TH","TN","TR","TW","UA","US","UY","VN","XK","ZA"],"type":"track","explicit":false,"duration_ms":161653,"external_urls":{"spotify":"https:\/\/open.spotify.com\/track\/7qAy6TR1MrSeUV8OpMlNS1"},"external_ids":{"isrc":"QMB621900210"}}},{"added_at":"2020-01-04T11:56:14Z","added_by":{"id":"petervschorn","external_urls":{"spotify":"https:\/\/open.spotify.com\/user\/petervschorn"},"href":"https:\/\/api.spotify.com\/v1\/users\/petervschorn","uri":"spotify:user:petervschorn","type":"user"},"is_local":false,"track":{"id":"0GDHyRVlxRVxofJfrw3aVF","name":"M.R.","album":{"images":[{"width":640,"url":"https:\/\/i.scdn.co\/image\/ab67616d0000b2739d45a127005f8a96652280bd","height":640},{"width":300,"url":"https:\/\/i.scdn.co\/image\/ab67616d00001e029d45a127005f8a96652280bd","height":300},{"width":64,"url":"https:\/\/i.scdn.co\/image\/ab67616d000048519d45a127005f8a96652280bd","height":64}],"release_date_precision":"day","release_date":"2019-06-14","id":"3vukTUpiENDHDoYTVrwqtz","uri":"spotify:album:3vukTUpiENDHDoYTVrwqtz","external_urls":{"spotify":"https:\/\/open.spotify.com\/album\/3vukTUpiENDHDoYTVrwqtz"},"href":"https:\/\/api.spotify.com\/v1\/albums\/3vukTUpiENDHDoYTVrwqtz","available_markets":["AD","AE","AL","AR","AT","AU","BA","BE","BG","BH","BO","BR","BY","CA","CH","CL","CO","CR","CY","CZ","DE","DK","DO","DZ","EC","EE","EG","ES","FI","FR","GB","GR","GT","HK","HN","HR","HU","ID","IE","IL","IN","IS","IT","JO","JP","KW","KZ","LB","LI","LT","LU","LV","MA","MC","MD","ME","MK","MT","MX","MY","NI","NL","NO","NZ","OM","PA","PE","PH","PL","PS","PT","PY","QA","RO","RS","RU","SA","SE","SG","SI","SK","SV","TH","TN","TR","TW","UA","US","UY","VN","XK","ZA"],"type":"album","name":"Jinx","artists":[{"type":"artist","id":"4kSGbjWGxTchKpIxXPJv0B","external_urls":{"spotify":"https:\/\/open.spotify.com\/artist\/4kSGbjWGxTchKpIxXPJv0B"},"name":"Crumb","uri":"spotify:artist:4kSGbjWGxTchKpIxXPJv0B","href":"https:\/\/api.spotify.com\/v1\/artists\/4kSGbjWGxTchKpIxXPJv0B"}]},"disc_number":1,"uri":"spotify:track:0GDHyRVlxRVxofJfrw3aVF","artists":[{"type":"artist","id":"4kSGbjWGxTchKpIxXPJv0B","external_urls":{"spotify":"https:\/\/open.spotify.com\/artist\/4kSGbjWGxTchKpIxXPJv0B"},"name":"Crumb","uri":"spotify:artist:4kSGbjWGxTchKpIxXPJv0B","href":"https:\/\/api.spotify.com\/v1\/artists\/4kSGbjWGxTchKpIxXPJv0B"}],"href":"https:\/\/api.spotify.com\/v1\/tracks\/0GDHyRVlxRVxofJfrw3aVF","is_local":false,"popularity":47,"available_markets":["AD","AE","AL","AR","AT","AU","BA","BE","BG","BH","BO","BR","BY","CA","CH","CL","CO","CR","CY","CZ","DE","DK","DO","DZ","EC","EE","EG","ES","FI","FR","GB","GR","GT","HK","HN","HR","HU","ID","IE","IL","IN","IS","IT","JO","JP","KW","KZ","LB","LI","LT","LU","LV","MA","MC","MD","ME","MK","MT","MX","MY","NI","NL","NO","NZ","OM","PA","PE","PH","PL","PS","PT","PY","QA","RO","RS","RU","SA","SE","SG","SI","SK","SV","TH","TN","TR","TW","UA","US","UY","VN","XK","ZA"],"type":"track","explicit":false,"duration_ms":217853,"external_urls":{"spotify":"https:\/\/open.spotify.com\/track\/0GDHyRVlxRVxofJfrw3aVF"},"external_ids":{"isrc":"QMB621900205"}}},{"added_at":"2020-01-04T11:58:22Z","added_by":{"id":"petervschorn","external_urls":{"spotify":"https:\/\/open.spotify.com\/user\/petervschorn"},"href":"https:\/\/api.spotify.com\/v1\/users\/petervschorn","uri":"spotify:user:petervschorn","type":"user"},"is_local":false,"track":{"id":"00kOafrPnrR7jQhxYYg777","name":"And It Never Ends","album":{"images":[{"width":640,"url":"https:\/\/i.scdn.co\/image\/ab67616d0000b2739d45a127005f8a96652280bd","height":640},{"width":300,"url":"https:\/\/i.scdn.co\/image\/ab67616d00001e029d45a127005f8a96652280bd","height":300},{"width":64,"url":"https:\/\/i.scdn.co\/image\/ab67616d000048519d45a127005f8a96652280bd","height":64}],"release_date_precision":"day","release_date":"2019-06-14","id":"3vukTUpiENDHDoYTVrwqtz","uri":"spotify:album:3vukTUpiENDHDoYTVrwqtz","external_urls":{"spotify":"https:\/\/open.spotify.com\/album\/3vukTUpiENDHDoYTVrwqtz"},"href":"https:\/\/api.spotify.com\/v1\/albums\/3vukTUpiENDHDoYTVrwqtz","available_markets":["AD","AE","AL","AR","AT","AU","BA","BE","BG","BH","BO","BR","BY","CA","CH","CL","CO","CR","CY","CZ","DE","DK","DO","DZ","EC","EE","EG","ES","FI","FR","GB","GR","GT","HK","HN","HR","HU","ID","IE","IL","IN","IS","IT","JO","JP","KW","KZ","LB","LI","LT","LU","LV","MA","MC","MD","ME","MK","MT","MX","MY","NI","NL","NO","NZ","OM","PA","PE","PH","PL","PS","PT","PY","QA","RO","RS","RU","SA","SE","SG","SI","SK","SV","TH","TN","TR","TW","UA","US","UY","VN","XK","ZA"],"type":"album","name":"Jinx","artists":[{"type":"artist","id":"4kSGbjWGxTchKpIxXPJv0B","external_urls":{"spotify":"https:\/\/open.spotify.com\/artist\/4kSGbjWGxTchKpIxXPJv0B"},"name":"Crumb","uri":"spotify:artist:4kSGbjWGxTchKpIxXPJv0B","href":"https:\/\/api.spotify.com\/v1\/artists\/4kSGbjWGxTchKpIxXPJv0B"}]},"disc_number":1,"uri":"spotify:track:00kOafrPnrR7jQhxYYg777","artists":[{"type":"artist","id":"4kSGbjWGxTchKpIxXPJv0B","external_urls":{"spotify":"https:\/\/open.spotify.com\/artist\/4kSGbjWGxTchKpIxXPJv0B"},"name":"Crumb","uri":"spotify:artist:4kSGbjWGxTchKpIxXPJv0B","href":"https:\/\/api.spotify.com\/v1\/artists\/4kSGbjWGxTchKpIxXPJv0B"}],"href":"https:\/\/api.spotify.com\/v1\/tracks\/00kOafrPnrR7jQhxYYg777","is_local":false,"popularity":45,"available_markets":["AD","AE","AL","AR","AT","AU","BA","BE","BG","BH","BO","BR","BY","CA","CH","CL","CO","CR","CY","CZ","DE","DK","DO","DZ","EC","EE","EG","ES","FI","FR","GB","GR","GT","HK","HN","HR","HU","ID","IE","IL","IN","IS","IT","JO","JP","KW","KZ","LB","LI","LT","LU","LV","MA","MC","MD","ME","MK","MT","MX","MY","NI","NL","NO","NZ","OM","PA","PE","PH","PL","PS","PT","PY","QA","RO","RS","RU","SA","SE","SG","SI","SK","SV","TH","TN","TR","TW","UA","US","UY","VN","XK","ZA"],"type":"track","explicit":false,"duration_ms":173333,"external_urls":{"spotify":"https:\/\/open.spotify.com\/track\/00kOafrPnrR7jQhxYYg777"},"external_ids":{"isrc":"QMB621900208"}}},{"added_at":"2020-01-04T16:54:06Z","added_by":{"id":"petervschorn","external_urls":{"spotify":"https:\/\/open.spotify.com\/user\/petervschorn"},"href":"https:\/\/api.spotify.com\/v1\/users\/petervschorn","uri":"spotify:user:petervschorn","type":"user"},"is_local":false,"track":{"id":"5h05V8HzaUBIEVlEnrzKDo","name":"Thirty-Nine","album":{"images":[{"width":640,"url":"https:\/\/i.scdn.co\/image\/ab67616d0000b2736147b24815415ae922d2a88f","height":640},{"width":300,"url":"https:\/\/i.scdn.co\/image\/ab67616d00001e026147b24815415ae922d2a88f","height":300},{"width":64,"url":"https:\/\/i.scdn.co\/image\/ab67616d000048516147b24815415ae922d2a88f","height":64}],"release_date_precision":"day","release_date":"2017-06-23","id":"2Q61Zm3rOli876QegmVY50","uri":"spotify:album:2Q61Zm3rOli876QegmVY50","external_urls":{"spotify":"https:\/\/open.spotify.com\/album\/2Q61Zm3rOli876QegmVY50"},"href":"https:\/\/api.spotify.com\/v1\/albums\/2Q61Zm3rOli876QegmVY50","available_markets":["AD","AE","AL","AR","AT","AU","BA","BE","BG","BH","BO","BR","BY","CA","CH","CL","CO","CR","CY","CZ","DE","DK","DO","DZ","EC","EE","EG","ES","FI","FR","GB","GR","GT","HK","HN","HR","HU","ID","IE","IL","IN","IS","IT","JO","JP","KW","KZ","LB","LI","LT","LU","LV","MA","MC","MD","ME","MK","MT","MX","MY","NI","NL","NO","NZ","OM","PA","PE","PH","PL","PS","PT","PY","QA","RO","RS","RU","SA","SE","SG","SI","SK","SV","TH","TN","TR","TW","UA","US","UY","VN","XK","ZA"],"type":"album","name":"Locket","artists":[{"type":"artist","id":"4kSGbjWGxTchKpIxXPJv0B","external_urls":{"spotify":"https:\/\/open.spotify.com\/artist\/4kSGbjWGxTchKpIxXPJv0B"},"name":"Crumb","uri":"spotify:artist:4kSGbjWGxTchKpIxXPJv0B","href":"https:\/\/api.spotify.com\/v1\/artists\/4kSGbjWGxTchKpIxXPJv0B"}]},"disc_number":1,"uri":"spotify:track:5h05V8HzaUBIEVlEnrzKDo","artists":[{"type":"artist","id":"4kSGbjWGxTchKpIxXPJv0B","external_urls":{"spotify":"https:\/\/open.spotify.com\/artist\/4kSGbjWGxTchKpIxXPJv0B"},"name":"Crumb","uri":"spotify:artist:4kSGbjWGxTchKpIxXPJv0B","href":"https:\/\/api.spotify.com\/v1\/artists\/4kSGbjWGxTchKpIxXPJv0B"}],"href":"https:\/\/api.spotify.com\/v1\/tracks\/5h05V8HzaUBIEVlEnrzKDo","is_local":false,"popularity":47,"available_markets":["AD","AE","AL","AR","AT","AU","BA","BE","BG","BH","BO","BR","BY","CA","CH","CL","CO","CR","CY","CZ","DE","DK","DO","DZ","EC","EE","EG","ES","FI","FR","GB","GR","GT","HK","HN","HR","HU","ID","IE","IL","IN","IS","IT","JO","JP","KW","KZ","LB","LI","LT","LU","LV","MA","MC","MD","ME","MK","MT","MX","MY","NI","NL","NO","NZ","OM","PA","PE","PH","PL","PS","PT","PY","QA","RO","RS","RU","SA","SE","SG","SI","SK","SV","TH","TN","TR","TW","UA","US","UY","VN","XK","ZA"],"type":"track","explicit":false,"duration_ms":279428,"external_urls":{"spotify":"https:\/\/open.spotify.com\/track\/5h05V8HzaUBIEVlEnrzKDo"},"external_ids":{"isrc":"TCADC1793182"}}},{"added_at":"2020-02-01T10:19:26Z","added_by":{"id":"petervschorn","external_urls":{"spotify":"https:\/\/open.spotify.com\/user\/petervschorn"},"href":"https:\/\/api.spotify.com\/v1\/users\/petervschorn","uri":"spotify:user:petervschorn","type":"user"},"is_local":false,"track":{"id":"4A4RgEk7hEFKwk9IUKdB8a","name":"Cracking","album":{"images":[{"width":640,"url":"https:\/\/i.scdn.co\/image\/ab67616d0000b2739d45a127005f8a96652280bd","height":640},{"width":300,"url":"https:\/\/i.scdn.co\/image\/ab67616d00001e029d45a127005f8a96652280bd","height":300},{"width":64,"url":"https:\/\/i.scdn.co\/image\/ab67616d000048519d45a127005f8a96652280bd","height":64}],"release_date_precision":"day","release_date":"2019-06-14","id":"3vukTUpiENDHDoYTVrwqtz","uri":"spotify:album:3vukTUpiENDHDoYTVrwqtz","external_urls":{"spotify":"https:\/\/open.spotify.com\/album\/3vukTUpiENDHDoYTVrwqtz"},"href":"https:\/\/api.spotify.com\/v1\/albums\/3vukTUpiENDHDoYTVrwqtz","available_markets":["AD","AE","AL","AR","AT","AU","BA","BE","BG","BH","BO","BR","BY","CA","CH","CL","CO","CR","CY","CZ","DE","DK","DO","DZ","EC","EE","EG","ES","FI","FR","GB","GR","GT","HK","HN","HR","HU","ID","IE","IL","IN","IS","IT","JO","JP","KW","KZ","LB","LI","LT","LU","LV","MA","MC","MD","ME","MK","MT","MX","MY","NI","NL","NO","NZ","OM","PA","PE","PH","PL","PS","PT","PY","QA","RO","RS","RU","SA","SE","SG","SI","SK","SV","TH","TN","TR","TW","UA","US","UY","VN","XK","ZA"],"type":"album","name":"Jinx","artists":[{"type":"artist","id":"4kSGbjWGxTchKpIxXPJv0B","external_urls":{"spotify":"https:\/\/open.spotify.com\/artist\/4kSGbjWGxTchKpIxXPJv0B"},"name":"Crumb","uri":"spotify:artist:4kSGbjWGxTchKpIxXPJv0B","href":"https:\/\/api.spotify.com\/v1\/artists\/4kSGbjWGxTchKpIxXPJv0B"}]},"disc_number":1,"uri":"spotify:track:4A4RgEk7hEFKwk9IUKdB8a","artists":[{"type":"artist","id":"4kSGbjWGxTchKpIxXPJv0B","external_urls":{"spotify":"https:\/\/open.spotify.com\/artist\/4kSGbjWGxTchKpIxXPJv0B"},"name":"Crumb","uri":"spotify:artist:4kSGbjWGxTchKpIxXPJv0B","href":"https:\/\/api.spotify.com\/v1\/artists\/4kSGbjWGxTchKpIxXPJv0B"}],"href":"https:\/\/api.spotify.com\/v1\/tracks\/4A4RgEk7hEFKwk9IUKdB8a","is_local":false,"popularity":48,"available_markets":["AD","AE","AL","AR","AT","AU","BA","BE","BG","BH","BO","BR","BY","CA","CH","CL","CO","CR","CY","CZ","DE","DK","DO","DZ","EC","EE","EG","ES","FI","FR","GB","GR","GT","HK","HN","HR","HU","ID","IE","IL","IN","IS","IT","JO","JP","KW","KZ","LB","LI","LT","LU","LV","MA","MC","MD","ME","MK","MT","MX","MY","NI","NL","NO","NZ","OM","PA","PE","PH","PL","PS","PT","PY","QA","RO","RS","RU","SA","SE","SG","SI","SK","SV","TH","TN","TR","TW","UA","US","UY","VN","XK","ZA"],"type":"track","explicit":false,"duration_ms":111986,"external_urls":{"spotify":"https:\/\/open.spotify.com\/track\/4A4RgEk7hEFKwk9IUKdB8a"},"external_ids":{"isrc":"QMB621900201"}}},{"added_at":"2020-02-03T00:54:47Z","added_by":{"id":"petervschorn","external_urls":{"spotify":"https:\/\/open.spotify.com\/user\/petervschorn"},"href":"https:\/\/api.spotify.com\/v1\/users\/petervschorn","uri":"spotify:user:petervschorn","type":"user"},"is_local":false,"track":{"id":"0N4ptfvrXtSe0rJ3VkmNmD","name":"Recently Played","album":{"images":[{"width":640,"url":"https:\/\/i.scdn.co\/image\/ab67616d0000b2736147b24815415ae922d2a88f","height":640},{"width":300,"url":"https:\/\/i.scdn.co\/image\/ab67616d00001e026147b24815415ae922d2a88f","height":300},{"width":64,"url":"https:\/\/i.scdn.co\/image\/ab67616d000048516147b24815415ae922d2a88f","height":64}],"release_date_precision":"day","release_date":"2017-06-23","id":"2Q61Zm3rOli876QegmVY50","uri":"spotify:album:2Q61Zm3rOli876QegmVY50","external_urls":{"spotify":"https:\/\/open.spotify.com\/album\/2Q61Zm3rOli876QegmVY50"},"href":"https:\/\/api.spotify.com\/v1\/albums\/2Q61Zm3rOli876QegmVY50","available_markets":["AD","AE","AL","AR","AT","AU","BA","BE","BG","BH","BO","BR","BY","CA","CH","CL","CO","CR","CY","CZ","DE","DK","DO","DZ","EC","EE","EG","ES","FI","FR","GB","GR","GT","HK","HN","HR","HU","ID","IE","IL","IN","IS","IT","JO","JP","KW","KZ","LB","LI","LT","LU","LV","MA","MC","MD","ME","MK","MT","MX","MY","NI","NL","NO","NZ","OM","PA","PE","PH","PL","PS","PT","PY","QA","RO","RS","RU","SA","SE","SG","SI","SK","SV","TH","TN","TR","TW","UA","US","UY","VN","XK","ZA"],"type":"album","name":"Locket","artists":[{"type":"artist","id":"4kSGbjWGxTchKpIxXPJv0B","external_urls":{"spotify":"https:\/\/open.spotify.com\/artist\/4kSGbjWGxTchKpIxXPJv0B"},"name":"Crumb","uri":"spotify:artist:4kSGbjWGxTchKpIxXPJv0B","href":"https:\/\/api.spotify.com\/v1\/artists\/4kSGbjWGxTchKpIxXPJv0B"}]},"disc_number":1,"uri":"spotify:track:0N4ptfvrXtSe0rJ3VkmNmD","artists":[{"type":"artist","id":"4kSGbjWGxTchKpIxXPJv0B","external_urls":{"spotify":"https:\/\/open.spotify.com\/artist\/4kSGbjWGxTchKpIxXPJv0B"},"name":"Crumb","uri":"spotify:artist:4kSGbjWGxTchKpIxXPJv0B","href":"https:\/\/api.spotify.com\/v1\/artists\/4kSGbjWGxTchKpIxXPJv0B"}],"href":"https:\/\/api.spotify.com\/v1\/tracks\/0N4ptfvrXtSe0rJ3VkmNmD","is_local":false,"popularity":51,"available_markets":["AD","AE","AL","AR","AT","AU","BA","BE","BG","BH","BO","BR","BY","CA","CH","CL","CO","CR","CY","CZ","DE","DK","DO","DZ","EC","EE","EG","ES","FI","FR","GB","GR","GT","HK","HN","HR","HU","ID","IE","IL","IN","IS","IT","JO","JP","KW","KZ","LB","LI","LT","LU","LV","MA","MC","MD","ME","MK","MT","MX","MY","NI","NL","NO","NZ","OM","PA","PE","PH","PL","PS","PT","PY","QA","RO","RS","RU","SA","SE","SG","SI","SK","SV","TH","TN","TR","TW","UA","US","UY","VN","XK","ZA"],"type":"track","explicit":false,"duration_ms":120454,"external_urls":{"spotify":"https:\/\/open.spotify.com\/track\/0N4ptfvrXtSe0rJ3VkmNmD"},"external_ids":{"isrc":"TCADC1793176"}}},{"added_at":"2020-02-06T21:58:38Z","added_by":{"id":"petervschorn","external_urls":{"spotify":"https:\/\/open.spotify.com\/user\/petervschorn"},"href":"https:\/\/api.spotify.com\/v1\/users\/petervschorn","uri":"spotify:user:petervschorn","type":"user"},"is_local":false,"track":{"id":"4jV8ThgB8B7BB4zBFH7rNe","name":"Vinta","album":{"images":[{"width":640,"url":"https:\/\/i.scdn.co\/image\/ab67616d0000b273864a5a2cf9f14df77fb7892a","height":640},{"width":300,"url":"https:\/\/i.scdn.co\/image\/ab67616d00001e02864a5a2cf9f14df77fb7892a","height":300},{"width":64,"url":"https:\/\/i.scdn.co\/image\/ab67616d00004851864a5a2cf9f14df77fb7892a","height":64}],"release_date_precision":"day","release_date":"2016-09-06","id":"61ewOkUPN4Ry8VaWlheFo3","uri":"spotify:album:61ewOkUPN4Ry8VaWlheFo3","external_urls":{"spotify":"https:\/\/open.spotify.com\/album\/61ewOkUPN4Ry8VaWlheFo3"},"href":"https:\/\/api.spotify.com\/v1\/albums\/61ewOkUPN4Ry8VaWlheFo3","available_markets":["AD","AE","AL","AR","AT","AU","BA","BE","BG","BH","BO","BR","BY","CA","CH","CL","CO","CR","CY","CZ","DE","DK","DO","DZ","EC","EE","EG","ES","FI","FR","GB","GR","GT","HK","HN","HR","HU","ID","IE","IL","IN","IS","IT","JO","JP","KW","KZ","LB","LI","LT","LU","LV","MA","MC","MD","ME","MK","MT","MX","MY","NI","NL","NO","NZ","OM","PA","PE","PH","PL","PS","PT","PY","QA","RO","RS","RU","SA","SE","SG","SI","SK","SV","TH","TN","TR","TW","UA","US","UY","VN","XK","ZA"],"type":"album","name":"Crumb","artists":[{"type":"artist","id":"4kSGbjWGxTchKpIxXPJv0B","external_urls":{"spotify":"https:\/\/open.spotify.com\/artist\/4kSGbjWGxTchKpIxXPJv0B"},"name":"Crumb","uri":"spotify:artist:4kSGbjWGxTchKpIxXPJv0B","href":"https:\/\/api.spotify.com\/v1\/artists\/4kSGbjWGxTchKpIxXPJv0B"}]},"disc_number":1,"uri":"spotify:track:4jV8ThgB8B7BB4zBFH7rNe","artists":[{"type":"artist","id":"4kSGbjWGxTchKpIxXPJv0B","external_urls":{"spotify":"https:\/\/open.spotify.com\/artist\/4kSGbjWGxTchKpIxXPJv0B"},"name":"Crumb","uri":"spotify:artist:4kSGbjWGxTchKpIxXPJv0B","href":"https:\/\/api.spotify.com\/v1\/artists\/4kSGbjWGxTchKpIxXPJv0B"}],"href":"https:\/\/api.spotify.com\/v1\/tracks\/4jV8ThgB8B7BB4zBFH7rNe","is_local":false,"popularity":54,"available_markets":["AD","AE","AL","AR","AT","AU","BA","BE","BG","BH","BO","BR","BY","CA","CH","CL","CO","CR","CY","CZ","DE","DK","DO","DZ","EC","EE","EG","ES","FI","FR","GB","GR","GT","HK","HN","HR","HU","ID","IE","IL","IN","IS","IT","JO","JP","KW","KZ","LB","LI","LT","LU","LV","MA","MC","MD","ME","MK","MT","MX","MY","NI","NL","NO","NZ","OM","PA","PE","PH","PL","PS","PT","PY","QA","RO","RS","RU","SA","SE","SG","SI","SK","SV","TH","TN","TR","TW","UA","US","UY","VN","XK","ZA"],"type":"track","explicit":false,"duration_ms":299970,"external_urls":{"spotify":"https:\/\/open.spotify.com\/track\/4jV8ThgB8B7BB4zBFH7rNe"},"external_ids":{"isrc":"TCACR1635433"}}},{"added_at":"2020-09-15T05:20:15Z","added_by":{"id":"petervschorn","external_urls":{"spotify":"https:\/\/open.spotify.com\/user\/petervschorn"},"href":"https:\/\/api.spotify.com\/v1\/users\/petervschorn","uri":"spotify:user:petervschorn","type":"user"},"is_local":false,"track":{"id":"1u7LOyLuApChbPeqMfXFKC","name":"Faces","album":{"images":[{"width":640,"url":"https:\/\/i.scdn.co\/image\/ab67616d0000b2739d45a127005f8a96652280bd","height":640},{"width":300,"url":"https:\/\/i.scdn.co\/image\/ab67616d00001e029d45a127005f8a96652280bd","height":300},{"width":64,"url":"https:\/\/i.scdn.co\/image\/ab67616d000048519d45a127005f8a96652280bd","height":64}],"release_date_precision":"day","release_date":"2019-06-14","id":"3vukTUpiENDHDoYTVrwqtz","uri":"spotify:album:3vukTUpiENDHDoYTVrwqtz","external_urls":{"spotify":"https:\/\/open.spotify.com\/album\/3vukTUpiENDHDoYTVrwqtz"},"href":"https:\/\/api.spotify.com\/v1\/albums\/3vukTUpiENDHDoYTVrwqtz","available_markets":["AD","AE","AL","AR","AT","AU","BA","BE","BG","BH","BO","BR","BY","CA","CH","CL","CO","CR","CY","CZ","DE","DK","DO","DZ","EC","EE","EG","ES","FI","FR","GB","GR","GT","HK","HN","HR","HU","ID","IE","IL","IN","IS","IT","JO","JP","KW","KZ","LB","LI","LT","LU","LV","MA","MC","MD","ME","MK","MT","MX","MY","NI","NL","NO","NZ","OM","PA","PE","PH","PL","PS","PT","PY","QA","RO","RS","RU","SA","SE","SG","SI","SK","SV","TH","TN","TR","TW","UA","US","UY","VN","XK","ZA"],"type":"album","name":"Jinx","artists":[{"type":"artist","id":"4kSGbjWGxTchKpIxXPJv0B","external_urls":{"spotify":"https:\/\/open.spotify.com\/artist\/4kSGbjWGxTchKpIxXPJv0B"},"name":"Crumb","uri":"spotify:artist:4kSGbjWGxTchKpIxXPJv0B","href":"https:\/\/api.spotify.com\/v1\/artists\/4kSGbjWGxTchKpIxXPJv0B"}]},"disc_number":1,"uri":"spotify:track:1u7LOyLuApChbPeqMfXFKC","artists":[{"type":"artist","id":"4kSGbjWGxTchKpIxXPJv0B","external_urls":{"spotify":"https:\/\/open.spotify.com\/artist\/4kSGbjWGxTchKpIxXPJv0B"},"name":"Crumb","uri":"spotify:artist:4kSGbjWGxTchKpIxXPJv0B","href":"https:\/\/api.spotify.com\/v1\/artists\/4kSGbjWGxTchKpIxXPJv0B"}],"href":"https:\/\/api.spotify.com\/v1\/tracks\/1u7LOyLuApChbPeqMfXFKC","is_local":false,"popularity":45,"available_markets":["AD","AE","AL","AR","AT","AU","BA","BE","BG","BH","BO","BR","BY","CA","CH","CL","CO","CR","CY","CZ","DE","DK","DO","DZ","EC","EE","EG","ES","FI","FR","GB","GR","GT","HK","HN","HR","HU","ID","IE","IL","IN","IS","IT","JO","JP","KW","KZ","LB","LI","LT","LU","LV","MA","MC","MD","ME","MK","MT","MX","MY","NI","NL","NO","NZ","OM","PA","PE","PH","PL","PS","PT","PY","QA","RO","RS","RU","SA","SE","SG","SI","SK","SV","TH","TN","TR","TW","UA","US","UY","VN","XK","ZA"],"type":"track","explicit":false,"duration_ms":129293,"external_urls":{"spotify":"https:\/\/open.spotify.com\/track\/1u7LOyLuApChbPeqMfXFKC"},"external_ids":{"isrc":"QMB621900209"}}},{"added_at":"2020-09-15T05:19:59Z","added_by":{"id":"petervschorn","external_urls":{"spotify":"https:\/\/open.spotify.com\/user\/petervschorn"},"href":"https:\/\/api.spotify.com\/v1\/users\/petervschorn","uri":"spotify:user:petervschorn","type":"user"},"is_local":false,"track":{"id":"476QHG5G8xxNI9VHTBFfjp","name":"Ghostride","album":{"images":[{"width":640,"url":"https:\/\/i.scdn.co\/image\/ab67616d0000b2739d45a127005f8a96652280bd","height":640},{"width":300,"url":"https:\/\/i.scdn.co\/image\/ab67616d00001e029d45a127005f8a96652280bd","height":300},{"width":64,"url":"https:\/\/i.scdn.co\/image\/ab67616d000048519d45a127005f8a96652280bd","height":64}],"release_date_precision":"day","release_date":"2019-06-14","id":"3vukTUpiENDHDoYTVrwqtz","uri":"spotify:album:3vukTUpiENDHDoYTVrwqtz","external_urls":{"spotify":"https:\/\/open.spotify.com\/album\/3vukTUpiENDHDoYTVrwqtz"},"href":"https:\/\/api.spotify.com\/v1\/albums\/3vukTUpiENDHDoYTVrwqtz","available_markets":["AD","AE","AL","AR","AT","AU","BA","BE","BG","BH","BO","BR","BY","CA","CH","CL","CO","CR","CY","CZ","DE","DK","DO","DZ","EC","EE","EG","ES","FI","FR","GB","GR","GT","HK","HN","HR","HU","ID","IE","IL","IN","IS","IT","JO","JP","KW","KZ","LB","LI","LT","LU","LV","MA","MC","MD","ME","MK","MT","MX","MY","NI","NL","NO","NZ","OM","PA","PE","PH","PL","PS","PT","PY","QA","RO","RS","RU","SA","SE","SG","SI","SK","SV","TH","TN","TR","TW","UA","US","UY","VN","XK","ZA"],"type":"album","name":"Jinx","artists":[{"type":"artist","id":"4kSGbjWGxTchKpIxXPJv0B","external_urls":{"spotify":"https:\/\/open.spotify.com\/artist\/4kSGbjWGxTchKpIxXPJv0B"},"name":"Crumb","uri":"spotify:artist:4kSGbjWGxTchKpIxXPJv0B","href":"https:\/\/api.spotify.com\/v1\/artists\/4kSGbjWGxTchKpIxXPJv0B"}]},"disc_number":1,"uri":"spotify:track:476QHG5G8xxNI9VHTBFfjp","artists":[{"type":"artist","id":"4kSGbjWGxTchKpIxXPJv0B","external_urls":{"spotify":"https:\/\/open.spotify.com\/artist\/4kSGbjWGxTchKpIxXPJv0B"},"name":"Crumb","uri":"spotify:artist:4kSGbjWGxTchKpIxXPJv0B","href":"https:\/\/api.spotify.com\/v1\/artists\/4kSGbjWGxTchKpIxXPJv0B"}],"href":"https:\/\/api.spotify.com\/v1\/tracks\/476QHG5G8xxNI9VHTBFfjp","is_local":false,"popularity":63,"available_markets":["AD","AE","AL","AR","AT","AU","BA","BE","BG","BH","BO","BR","BY","CA","CH","CL","CO","CR","CY","CZ","DE","DK","DO","DZ","EC","EE","EG","ES","FI","FR","GB","GR","GT","HK","HN","HR","HU","ID","IE","IL","IN","IS","IT","JO","JP","KW","KZ","LB","LI","LT","LU","LV","MA","MC","MD","ME","MK","MT","MX","MY","NI","NL","NO","NZ","OM","PA","PE","PH","PL","PS","PT","PY","QA","RO","RS","RU","SA","SE","SG","SI","SK","SV","TH","TN","TR","TW","UA","US","UY","VN","XK","ZA"],"type":"track","explicit":false,"duration_ms":126120,"external_urls":{"spotify":"https:\/\/open.spotify.com\/track\/476QHG5G8xxNI9VHTBFfjp"},"external_ids":{"isrc":"QMB621900203"}}},{"added_at":"2020-09-11T10:55:45Z","added_by":{"id":"petervschorn","external_urls":{"spotify":"https:\/\/open.spotify.com\/user\/petervschorn"},"href":"https:\/\/api.spotify.com\/v1\/users\/petervschorn","uri":"spotify:user:petervschorn","type":"user"},"is_local":false,"track":{"id":"4rL1OrbBCOD5hDgXWPCqW3","name":"Bones","album":{"images":[{"width":640,"url":"https:\/\/i.scdn.co\/image\/ab67616d0000b273864a5a2cf9f14df77fb7892a","height":640},{"width":300,"url":"https:\/\/i.scdn.co\/image\/ab67616d00001e02864a5a2cf9f14df77fb7892a","height":300},{"width":64,"url":"https:\/\/i.scdn.co\/image\/ab67616d00004851864a5a2cf9f14df77fb7892a","height":64}],"release_date_precision":"day","release_date":"2016-09-06","id":"61ewOkUPN4Ry8VaWlheFo3","uri":"spotify:album:61ewOkUPN4Ry8VaWlheFo3","external_urls":{"spotify":"https:\/\/open.spotify.com\/album\/61ewOkUPN4Ry8VaWlheFo3"},"href":"https:\/\/api.spotify.com\/v1\/albums\/61ewOkUPN4Ry8VaWlheFo3","available_markets":["AD","AE","AL","AR","AT","AU","BA","BE","BG","BH","BO","BR","BY","CA","CH","CL","CO","CR","CY","CZ","DE","DK","DO","DZ","EC","EE","EG","ES","FI","FR","GB","GR","GT","HK","HN","HR","HU","ID","IE","IL","IN","IS","IT","JO","JP","KW","KZ","LB","LI","LT","LU","LV","MA","MC","MD","ME","MK","MT","MX","MY","NI","NL","NO","NZ","OM","PA","PE","PH","PL","PS","PT","PY","QA","RO","RS","RU","SA","SE","SG","SI","SK","SV","TH","TN","TR","TW","UA","US","UY","VN","XK","ZA"],"type":"album","name":"Crumb","artists":[{"type":"artist","id":"4kSGbjWGxTchKpIxXPJv0B","external_urls":{"spotify":"https:\/\/open.spotify.com\/artist\/4kSGbjWGxTchKpIxXPJv0B"},"name":"Crumb","uri":"spotify:artist:4kSGbjWGxTchKpIxXPJv0B","href":"https:\/\/api.spotify.com\/v1\/artists\/4kSGbjWGxTchKpIxXPJv0B"}]},"disc_number":1,"uri":"spotify:track:4rL1OrbBCOD5hDgXWPCqW3","artists":[{"type":"artist","id":"4kSGbjWGxTchKpIxXPJv0B","external_urls":{"spotify":"https:\/\/open.spotify.com\/artist\/4kSGbjWGxTchKpIxXPJv0B"},"name":"Crumb","uri":"spotify:artist:4kSGbjWGxTchKpIxXPJv0B","href":"https:\/\/api.spotify.com\/v1\/artists\/4kSGbjWGxTchKpIxXPJv0B"}],"href":"https:\/\/api.spotify.com\/v1\/tracks\/4rL1OrbBCOD5hDgXWPCqW3","is_local":false,"popularity":59,"available_markets":["AD","AE","AL","AR","AT","AU","BA","BE","BG","BH","BO","BR","BY","CA","CH","CL","CO","CR","CY","CZ","DE","DK","DO","DZ","EC","EE","EG","ES","FI","FR","GB","GR","GT","HK","HN","HR","HU","ID","IE","IL","IN","IS","IT","JO","JP","KW","KZ","LB","LI","LT","LU","LV","MA","MC","MD","ME","MK","MT","MX","MY","NI","NL","NO","NZ","OM","PA","PE","PH","PL","PS","PT","PY","QA","RO","RS","RU","SA","SE","SG","SI","SK","SV","TH","TN","TR","TW","UA","US","UY","VN","XK","ZA"],"type":"track","explicit":false,"duration_ms":193981,"external_urls":{"spotify":"https:\/\/open.spotify.com\/track\/4rL1OrbBCOD5hDgXWPCqW3"},"external_ids":{"isrc":"TCACR1635419"}}},{"added_at":"2020-09-11T10:37:23Z","added_by":{"id":"petervschorn","external_urls":{"spotify":"https:\/\/open.spotify.com\/user\/petervschorn"},"href":"https:\/\/api.spotify.com\/v1\/users\/petervschorn","uri":"spotify:user:petervschorn","type":"user"},"is_local":false,"track":{"id":"6IqcbrxCPlbXaQuNoQMB8v","name":"Fall Down","album":{"images":[{"width":640,"url":"https:\/\/i.scdn.co\/image\/ab67616d0000b2739d45a127005f8a96652280bd","height":640},{"width":300,"url":"https:\/\/i.scdn.co\/image\/ab67616d00001e029d45a127005f8a96652280bd","height":300},{"width":64,"url":"https:\/\/i.scdn.co\/image\/ab67616d000048519d45a127005f8a96652280bd","height":64}],"release_date_precision":"day","release_date":"2019-06-14","id":"3vukTUpiENDHDoYTVrwqtz","uri":"spotify:album:3vukTUpiENDHDoYTVrwqtz","external_urls":{"spotify":"https:\/\/open.spotify.com\/album\/3vukTUpiENDHDoYTVrwqtz"},"href":"https:\/\/api.spotify.com\/v1\/albums\/3vukTUpiENDHDoYTVrwqtz","available_markets":["AD","AE","AL","AR","AT","AU","BA","BE","BG","BH","BO","BR","BY","CA","CH","CL","CO","CR","CY","CZ","DE","DK","DO","DZ","EC","EE","EG","ES","FI","FR","GB","GR","GT","HK","HN","HR","HU","ID","IE","IL","IN","IS","IT","JO","JP","KW","KZ","LB","LI","LT","LU","LV","MA","MC","MD","ME","MK","MT","MX","MY","NI","NL","NO","NZ","OM","PA","PE","PH","PL","PS","PT","PY","QA","RO","RS","RU","SA","SE","SG","SI","SK","SV","TH","TN","TR","TW","UA","US","UY","VN","XK","ZA"],"type":"album","name":"Jinx","artists":[{"type":"artist","id":"4kSGbjWGxTchKpIxXPJv0B","external_urls":{"spotify":"https:\/\/open.spotify.com\/artist\/4kSGbjWGxTchKpIxXPJv0B"},"name":"Crumb","uri":"spotify:artist:4kSGbjWGxTchKpIxXPJv0B","href":"https:\/\/api.spotify.com\/v1\/artists\/4kSGbjWGxTchKpIxXPJv0B"}]},"disc_number":1,"uri":"spotify:track:6IqcbrxCPlbXaQuNoQMB8v","artists":[{"type":"artist","id":"4kSGbjWGxTchKpIxXPJv0B","external_urls":{"spotify":"https:\/\/open.spotify.com\/artist\/4kSGbjWGxTchKpIxXPJv0B"},"name":"Crumb","uri":"spotify:artist:4kSGbjWGxTchKpIxXPJv0B","href":"https:\/\/api.spotify.com\/v1\/artists\/4kSGbjWGxTchKpIxXPJv0B"}],"href":"https:\/\/api.spotify.com\/v1\/tracks\/6IqcbrxCPlbXaQuNoQMB8v","is_local":false,"popularity":51,"available_markets":["AD","AE","AL","AR","AT","AU","BA","BE","BG","BH","BO","BR","BY","CA","CH","CL","CO","CR","CY","CZ","DE","DK","DO","DZ","EC","EE","EG","ES","FI","FR","GB","GR","GT","HK","HN","HR","HU","ID","IE","IL","IN","IS","IT","JO","JP","KW","KZ","LB","LI","LT","LU","LV","MA","MC","MD","ME","MK","MT","MX","MY","NI","NL","NO","NZ","OM","PA","PE","PH","PL","PS","PT","PY","QA","RO","RS","RU","SA","SE","SG","SI","SK","SV","TH","TN","TR","TW","UA","US","UY","VN","XK","ZA"],"type":"track","explicit":false,"duration_ms":173000,"external_urls":{"spotify":"https:\/\/open.spotify.com\/track\/6IqcbrxCPlbXaQuNoQMB8v"},"external_ids":{"isrc":"QMB621900204"}}}],"href":"https:\/\/api.spotify.com\/v1\/playlists\/33yLOStnp2emkEA76ew1Dz\/tracks?offset=0&limit=100&additional_types=track,episode","offset":0,"limit":100},"uri":"spotify:playlist:33yLOStnp2emkEA76ew1Dz","href":"https:\/\/api.spotify.com\/v1\/playlists\/33yLOStnp2emkEA76ew1Dz?additional_types=track,episode","owner":{"id":"petervschorn","display_name":"petervschorn","external_urls":{"spotify":"https:\/\/open.spotify.com\/user\/petervschorn"},"href":"https:\/\/api.spotify.com\/v1\/users\/petervschorn","uri":"spotify:user:petervschorn","type":"user"},"name":"Crumb","collaborative":false,"images":[{"url":"https:\/\/i.scdn.co\/image\/ab67706c0000bebbf61e7477acefd870ab26cc7a"}],"followers":{"total":0},"public":true,"snapshot_id":"NTgzLDZjZGY2ZGYyYjgwNGQ3NDdkYjAwYjIwYmU4Mjk0YzMyODRiOThmMmU="}