{"primaryContentSections":[{"kind":"declarations","declarations":[{"tokens":[{"kind":"keyword","text":"init"},{"kind":"text","text":"("},{"kind":"externalParam","text":"name"},{"kind":"text","text":": "},{"kind":"typeIdentifier","text":"String","preciseIdentifier":"s:SS"},{"kind":"text","text":", "},{"kind":"externalParam","text":"audiobook"},{"kind":"text","text":": "},{"kind":"typeIdentifier","identifier":"doc:\/\/SpotifyWebAPI\/documentation\/SpotifyWebAPI\/Audiobook","preciseIdentifier":"s:13SpotifyWebAPI9AudiobookV","text":"Audiobook"},{"kind":"text","text":"? = nil, "},{"kind":"externalParam","text":"chapterNumber"},{"kind":"text","text":": "},{"kind":"typeIdentifier","text":"Int","preciseIdentifier":"s:Si"},{"kind":"text","text":", "},{"kind":"externalParam","text":"audioPreviewURL"},{"kind":"text","text":": "},{"kind":"typeIdentifier","text":"URL","preciseIdentifier":"s:10Foundation3URLV"},{"kind":"text","text":"? = nil, "},{"kind":"externalParam","text":"description"},{"kind":"text","text":": "},{"kind":"typeIdentifier","text":"String","preciseIdentifier":"s:SS"},{"kind":"text","text":", "},{"kind":"externalParam","text":"htmlDescription"},{"kind":"text","text":": "},{"kind":"typeIdentifier","text":"String","preciseIdentifier":"s:SS"},{"kind":"text","text":", "},{"kind":"externalParam","text":"resumePoint"},{"kind":"text","text":": "},{"kind":"typeIdentifier","identifier":"doc:\/\/SpotifyWebAPI\/documentation\/SpotifyWebAPI\/ResumePoint","preciseIdentifier":"s:13SpotifyWebAPI11ResumePointV","text":"ResumePoint"},{"kind":"text","text":"? = nil, "},{"kind":"externalParam","text":"durationMS"},{"kind":"text","text":": "},{"kind":"typeIdentifier","text":"Int","preciseIdentifier":"s:Si"},{"kind":"text","text":", "},{"kind":"externalParam","text":"isExplicit"},{"kind":"text","text":": "},{"kind":"typeIdentifier","text":"Bool","preciseIdentifier":"s:Sb"},{"kind":"text","text":", "},{"kind":"externalParam","text":"releaseDate"},{"kind":"text","text":": "},{"kind":"typeIdentifier","text":"Date","preciseIdentifier":"s:10Foundation4DateV"},{"kind":"text","text":"? = nil, "},{"kind":"externalParam","text":"uri"},{"kind":"text","text":": "},{"kind":"typeIdentifier","text":"String","preciseIdentifier":"s:SS"},{"kind":"text","text":", "},{"kind":"externalParam","text":"id"},{"kind":"text","text":": "},{"kind":"typeIdentifier","text":"String","preciseIdentifier":"s:SS"},{"kind":"text","text":", "},{"kind":"externalParam","text":"images"},{"kind":"text","text":": ["},{"kind":"typeIdentifier","identifier":"doc:\/\/SpotifyWebAPI\/documentation\/SpotifyWebAPI\/SpotifyImage","preciseIdentifier":"s:13SpotifyWebAPI0A5ImageV","text":"SpotifyImage"},{"kind":"text","text":"]? = nil, "},{"kind":"externalParam","text":"availableMarkets"},{"kind":"text","text":": ["},{"kind":"typeIdentifier","text":"String","preciseIdentifier":"s:SS"},{"kind":"text","text":"]? = nil, "},{"kind":"externalParam","text":"href"},{"kind":"text","text":": "},{"kind":"typeIdentifier","text":"URL","preciseIdentifier":"s:10Foundation3URLV"},{"kind":"text","text":", "},{"kind":"externalParam","text":"isPlayable"},{"kind":"text","text":": "},{"kind":"typeIdentifier","text":"Bool","preciseIdentifier":"s:Sb"},{"kind":"text","text":"?, "},{"kind":"externalParam","text":"externalURLs"},{"kind":"text","text":": ["},{"kind":"typeIdentifier","text":"String","preciseIdentifier":"s:SS"},{"kind":"text","text":" : "},{"kind":"typeIdentifier","text":"URL","preciseIdentifier":"s:10Foundation3URLV"},{"kind":"text","text":"]? = nil, "},{"kind":"externalParam","text":"languages"},{"kind":"text","text":": ["},{"kind":"typeIdentifier","text":"String","preciseIdentifier":"s:SS"},{"kind":"text","text":"], "},{"kind":"externalParam","text":"restrictions"},{"kind":"text","text":": ["},{"kind":"typeIdentifier","text":"String","preciseIdentifier":"s:SS"},{"kind":"text","text":" : "},{"kind":"typeIdentifier","text":"String","preciseIdentifier":"s:SS"},{"kind":"text","text":"]? = nil, "},{"kind":"externalParam","text":"releaseDatePrecision"},{"kind":"text","text":": "},{"kind":"typeIdentifier","text":"String","preciseIdentifier":"s:SS"},{"kind":"text","text":"? = nil)"}],"languages":["swift"],"platforms":["macOS"]}]},{"kind":"parameters","parameters":[{"name":"name","content":[{"type":"paragraph","inlineContent":[{"type":"text","text":"The name of the audiobook chapter."}]}]},{"name":"audiobook","content":[{"type":"paragraph","inlineContent":[{"type":"text","text":"The audiobook that this chapter belongs to."}]}]},{"name":"chapterNumber","content":[{"type":"paragraph","inlineContent":[{"type":"text","text":"The zero-based index of this chapter in the audiobook it"},{"type":"text","text":" "},{"type":"text","text":"belongs to."}]}]},{"name":"audioPreviewURL","content":[{"type":"paragraph","inlineContent":[{"type":"text","text":"A URL to a 30 second preview (MP3 format) of this"},{"type":"text","text":" "},{"type":"text","text":"chapter, if available."}]}]},{"name":"description","content":[{"type":"paragraph","inlineContent":[{"type":"text","text":"A description of the chapter. See also"},{"type":"text","text":" "},{"type":"reference","isActive":true,"identifier":"doc:\/\/SpotifyWebAPI\/documentation\/SpotifyWebAPI\/AudiobookChapter\/htmlDescription"},{"type":"text","text":"."}]}]},{"name":"htmlDescription","content":[{"type":"paragraph","inlineContent":[{"type":"text","text":"A description of the chapter which may contain HTML"},{"type":"text","text":" "},{"type":"text","text":"tags. See also "},{"type":"reference","isActive":true,"identifier":"doc:\/\/SpotifyWebAPI\/documentation\/SpotifyWebAPI\/AudiobookChapter\/description"},{"type":"text","text":"."}]}]},{"name":"resumePoint","content":[{"type":"paragraph","inlineContent":[{"type":"text","text":"The user’s most recent position in the chapter. Non-"},{"type":"codeVoice","code":"nil"},{"type":"text","text":" "},{"type":"text","text":"only if the application has been authorized for the"},{"type":"text","text":" "},{"type":"reference","isActive":true,"identifier":"doc:\/\/SpotifyWebAPI\/documentation\/SpotifyWebAPI\/Scope\/userReadPlaybackPosition"},{"type":"text","text":" scope."}]}]},{"name":"durationMS","content":[{"type":"paragraph","inlineContent":[{"type":"text","text":"The chapter length, in milliseconds."}]}]},{"name":"isExplicit","content":[{"type":"paragraph","inlineContent":[{"type":"text","text":"Whether or not the chapter is explicit. "},{"type":"codeVoice","code":"false"},{"type":"text","text":" if unknown."}]}]},{"name":"releaseDate","content":[{"type":"paragraph","inlineContent":[{"type":"text","text":"The date the chapter was released. See also"},{"type":"text","text":" "},{"type":"reference","isActive":true,"identifier":"doc:\/\/SpotifyWebAPI\/documentation\/SpotifyWebAPI\/AudiobookChapter\/releaseDatePrecision"},{"type":"text","text":"."}]}]},{"name":"uri","content":[{"type":"paragraph","inlineContent":[{"type":"text","text":"The "},{"type":"reference","isActive":true,"identifier":"https:\/\/developer.spotify.com\/documentation\/web-api\/#spotify-uris-and-ids"},{"type":"text","text":" for the chapter."}]}]},{"name":"id","content":[{"type":"paragraph","inlineContent":[{"type":"text","text":"The "},{"type":"reference","isActive":true,"identifier":"https:\/\/developer.spotify.com\/documentation\/web-api\/#spotify-uris-and-ids"},{"type":"text","text":" for the chapter."}]}]},{"name":"images","content":[{"type":"paragraph","inlineContent":[{"type":"text","text":"Images for the chapter in various sizes, widest first."}]}]},{"name":"availableMarkets","content":[{"type":"paragraph","inlineContent":[{"type":"text","text":"A list of the countries in which the chapter can be"},{"type":"text","text":" "},{"type":"text","text":"played, identified by their "},{"type":"reference","isActive":true,"identifier":"http:\/\/en.wikipedia.org\/wiki\/ISO_3166-1_alpha-2"},{"type":"text","text":" codes."}]}]},{"name":"href","content":[{"type":"paragraph","inlineContent":[{"type":"text","text":"A link to the Spotify web API endpoint providing the full chapter"},{"type":"text","text":" "},{"type":"text","text":"object. Use "},{"type":"reference","isActive":true,"identifier":"doc:\/\/SpotifyWebAPI\/documentation\/SpotifyWebAPI\/SpotifyAPI\/getFromHref(_:responseType:)"},{"type":"text","text":", passing in"},{"type":"text","text":" "},{"type":"reference","isActive":true,"identifier":"doc:\/\/SpotifyWebAPI\/documentation\/SpotifyWebAPI\/AudiobookChapter"},{"type":"text","text":" as the response type to retrieve the results."}]}]},{"name":"isPlayable","content":[{"type":"paragraph","inlineContent":[{"type":"text","text":""},{"type":"codeVoice","code":"true"},{"type":"text","text":" if the chapter is playable in the given market."},{"type":"text","text":" "},{"type":"text","text":"Else, "},{"type":"codeVoice","code":"false"},{"type":"text","text":"."}]}]},{"name":"externalURLs","content":[{"type":"paragraph","inlineContent":[{"type":"text","text":"Known external urls for the chapter."},{"type":"text","text":" "},{"type":"text","text":"- key: The type of the URL, for example: “spotify” - The "},{"type":"reference","isActive":true,"identifier":"https:\/\/developer.spotify.com\/documentation\/web-api\/#spotify-uris-and-ids"},{"type":"text","text":" for the object."},{"type":"text","text":" "},{"type":"text","text":"- value: An external, public URL to the object."}]}]},{"name":"languages","content":[{"type":"paragraph","inlineContent":[{"type":"text","text":"A list of the languages used in the chapter, identified by"},{"type":"text","text":" "},{"type":"text","text":"their "},{"type":"reference","isActive":true,"identifier":"https:\/\/en.wikipedia.org\/wiki\/ISO_639"},{"type":"text","text":" codes."}]}]},{"name":"restrictions","content":[{"type":"paragraph","inlineContent":[{"type":"text","text":"Part of the response when a content restriction is"},{"type":"text","text":" "},{"type":"text","text":"applied. The key will be “reason”, and the value will be one of the"},{"type":"text","text":" "},{"type":"text","text":"following:"},{"type":"text","text":" "},{"type":"text","text":"* “payment_required” - The content item requires payment to be"},{"type":"text","text":" "},{"type":"text","text":"played."},{"type":"text","text":" "},{"type":"text","text":"* “market” - The content item is not available in the given market."},{"type":"text","text":" "},{"type":"text","text":"* “product” - The content item is not available for the user’s"},{"type":"text","text":" "},{"type":"text","text":"subscription type."},{"type":"text","text":" "},{"type":"text","text":"* “explicit” - The content item is explicit and the user’s account"},{"type":"text","text":" "},{"type":"text","text":"is set to not play explicit content."},{"type":"text","text":" "},{"type":"text","text":"Additional reasons and additional keys may be added in the future."}]}]},{"name":"releaseDatePrecision","content":[{"type":"paragraph","inlineContent":[{"type":"text","text":"The precision with which "},{"type":"reference","isActive":true,"identifier":"doc:\/\/SpotifyWebAPI\/documentation\/SpotifyWebAPI\/AudiobookChapter\/releaseDate"},{"type":"text","text":" is"},{"type":"text","text":" "},{"type":"text","text":"known: “year”, “month”, or “day”."}]}]}]}],"schemaVersion":{"major":0,"minor":3,"patch":0},"sections":[],"variants":[{"paths":["\/documentation\/spotifywebapi\/audiobookchapter\/init(name:audiobook:chapternumber:audiopreviewurl:description:htmldescription:resumepoint:durationms:isexplicit:releasedate:uri:id:images:availablemarkets:href:isplayable:externalurls:languages:restrictions:releasedateprecision:)"],"traits":[{"interfaceLanguage":"swift"}]}],"identifier":{"url":"doc:\/\/SpotifyWebAPI\/documentation\/SpotifyWebAPI\/AudiobookChapter\/init(name:audiobook:chapterNumber:audioPreviewURL:description:htmlDescription:resumePoint:durationMS:isExplicit:releaseDate:uri:id:images:availableMarkets:href:isPlayable:externalURLs:languages:restrictions:releaseDatePrecision:)","interfaceLanguage":"swift"},"abstract":[{"type":"text","text":"Creates a Spotify audiobook chapter."}],"kind":"symbol","metadata":{"fragments":[{"kind":"identifier","text":"init"},{"kind":"text","text":"("},{"kind":"externalParam","text":"name"},{"kind":"text","text":": "},{"kind":"typeIdentifier","text":"String","preciseIdentifier":"s:SS"},{"kind":"text","text":", "},{"kind":"externalParam","text":"audiobook"},{"kind":"text","text":": "},{"kind":"typeIdentifier","text":"Audiobook","preciseIdentifier":"s:13SpotifyWebAPI9AudiobookV"},{"kind":"text","text":"?, "},{"kind":"externalParam","text":"chapterNumber"},{"kind":"text","text":": "},{"kind":"typeIdentifier","text":"Int","preciseIdentifier":"s:Si"},{"kind":"text","text":", "},{"kind":"externalParam","text":"audioPreviewURL"},{"kind":"text","text":": "},{"kind":"typeIdentifier","text":"URL","preciseIdentifier":"s:10Foundation3URLV"},{"kind":"text","text":"?, "},{"kind":"externalParam","text":"description"},{"kind":"text","text":": "},{"kind":"typeIdentifier","text":"String","preciseIdentifier":"s:SS"},{"kind":"text","text":", "},{"kind":"externalParam","text":"htmlDescription"},{"kind":"text","text":": "},{"kind":"typeIdentifier","text":"String","preciseIdentifier":"s:SS"},{"kind":"text","text":", "},{"kind":"externalParam","text":"resumePoint"},{"kind":"text","text":": "},{"kind":"typeIdentifier","text":"ResumePoint","preciseIdentifier":"s:13SpotifyWebAPI11ResumePointV"},{"kind":"text","text":"?, "},{"kind":"externalParam","text":"durationMS"},{"kind":"text","text":": "},{"kind":"typeIdentifier","text":"Int","preciseIdentifier":"s:Si"},{"kind":"text","text":", "},{"kind":"externalParam","text":"isExplicit"},{"kind":"text","text":": "},{"kind":"typeIdentifier","text":"Bool","preciseIdentifier":"s:Sb"},{"kind":"text","text":", "},{"kind":"externalParam","text":"releaseDate"},{"kind":"text","text":": "},{"kind":"typeIdentifier","text":"Date","preciseIdentifier":"s:10Foundation4DateV"},{"kind":"text","text":"?, "},{"kind":"externalParam","text":"uri"},{"kind":"text","text":": "},{"kind":"typeIdentifier","text":"String","preciseIdentifier":"s:SS"},{"kind":"text","text":", "},{"kind":"externalParam","text":"id"},{"kind":"text","text":": "},{"kind":"typeIdentifier","text":"String","preciseIdentifier":"s:SS"},{"kind":"text","text":", "},{"kind":"externalParam","text":"images"},{"kind":"text","text":": ["},{"kind":"typeIdentifier","text":"SpotifyImage","preciseIdentifier":"s:13SpotifyWebAPI0A5ImageV"},{"kind":"text","text":"]?, "},{"kind":"externalParam","text":"availableMarkets"},{"kind":"text","text":": ["},{"kind":"typeIdentifier","text":"String","preciseIdentifier":"s:SS"},{"kind":"text","text":"]?, "},{"kind":"externalParam","text":"href"},{"kind":"text","text":": "},{"kind":"typeIdentifier","text":"URL","preciseIdentifier":"s:10Foundation3URLV"},{"kind":"text","text":", "},{"kind":"externalParam","text":"isPlayable"},{"kind":"text","text":": "},{"kind":"typeIdentifier","text":"Bool","preciseIdentifier":"s:Sb"},{"kind":"text","text":"?, "},{"kind":"externalParam","text":"externalURLs"},{"kind":"text","text":": ["},{"kind":"typeIdentifier","text":"String","preciseIdentifier":"s:SS"},{"kind":"text","text":" : "},{"kind":"typeIdentifier","text":"URL","preciseIdentifier":"s:10Foundation3URLV"},{"kind":"text","text":"]?, "},{"kind":"externalParam","text":"languages"},{"kind":"text","text":": ["},{"kind":"typeIdentifier","text":"String","preciseIdentifier":"s:SS"},{"kind":"text","text":"], "},{"kind":"externalParam","text":"restrictions"},{"kind":"text","text":": ["},{"kind":"typeIdentifier","text":"String","preciseIdentifier":"s:SS"},{"kind":"text","text":" : "},{"kind":"typeIdentifier","text":"String","preciseIdentifier":"s:SS"},{"kind":"text","text":"]?, "},{"kind":"externalParam","text":"releaseDatePrecision"},{"kind":"text","text":": "},{"kind":"typeIdentifier","text":"String","preciseIdentifier":"s:SS"},{"kind":"text","text":"?)"}],"title":"init(name:audiobook:chapterNumber:audioPreviewURL:description:htmlDescription:resumePoint:durationMS:isExplicit:releaseDate:uri:id:images:availableMarkets:href:isPlayable:externalURLs:languages:restrictions:releaseDatePrecision:)","roleHeading":"Initializer","role":"symbol","symbolKind":"init","externalID":"s:13SpotifyWebAPI16AudiobookChapterV4name9audiobook13chapterNumber15audioPreviewURL11description15htmlDescription11resumePoint10durationMS10isExplicit11releaseDate3uri2id6images16availableMarkets4href0T8Playable12externalURLs9languages12restrictions0vW9PrecisionACSS_AA0D0VSgSi10Foundation0L0VSgS2SAA06ResumeQ0VSgSiSbA_0W0VSgS2SSayAA0A5ImageVGSgSaySSGSgA1_SbSgSDySSA1_GSgA13_SDyS2SGSgSSSgtcfc","modules":[{"name":"SpotifyWebAPI"}]},"hierarchy":{"paths":[["doc:\/\/SpotifyWebAPI\/documentation\/SpotifyWebAPI","doc:\/\/SpotifyWebAPI\/documentation\/SpotifyWebAPI\/Audiobook-Objects","doc:\/\/SpotifyWebAPI\/documentation\/SpotifyWebAPI\/AudiobookChapter"]]},"references":{"doc://SpotifyWebAPI/documentation/SpotifyWebAPI/AudiobookChapter/init(name:audiobook:chapterNumber:audioPreviewURL:description:htmlDescription:resumePoint:durationMS:isExplicit:releaseDate:uri:id:images:availableMarkets:href:isPlayable:externalURLs:languages:restrictions:releaseDatePrecision:)":{"role":"symbol","title":"init(name:audiobook:chapterNumber:audioPreviewURL:description:htmlDescription:resumePoint:durationMS:isExplicit:releaseDate:uri:id:images:availableMarkets:href:isPlayable:externalURLs:languages:restrictions:releaseDatePrecision:)","fragments":[{"kind":"identifier","text":"init"},{"kind":"text","text":"("},{"kind":"externalParam","text":"name"},{"kind":"text","text":": "},{"kind":"typeIdentifier","text":"String","preciseIdentifier":"s:SS"},{"kind":"text","text":", "},{"kind":"externalParam","text":"audiobook"},{"kind":"text","text":": "},{"kind":"typeIdentifier","text":"Audiobook","preciseIdentifier":"s:13SpotifyWebAPI9AudiobookV"},{"kind":"text","text":"?, "},{"kind":"externalParam","text":"chapterNumber"},{"kind":"text","text":": "},{"kind":"typeIdentifier","text":"Int","preciseIdentifier":"s:Si"},{"kind":"text","text":", "},{"kind":"externalParam","text":"audioPreviewURL"},{"kind":"text","text":": "},{"kind":"typeIdentifier","text":"URL","preciseIdentifier":"s:10Foundation3URLV"},{"kind":"text","text":"?, "},{"kind":"externalParam","text":"description"},{"kind":"text","text":": "},{"kind":"typeIdentifier","text":"String","preciseIdentifier":"s:SS"},{"kind":"text","text":", "},{"kind":"externalParam","text":"htmlDescription"},{"kind":"text","text":": "},{"kind":"typeIdentifier","text":"String","preciseIdentifier":"s:SS"},{"kind":"text","text":", "},{"kind":"externalParam","text":"resumePoint"},{"kind":"text","text":": "},{"kind":"typeIdentifier","text":"ResumePoint","preciseIdentifier":"s:13SpotifyWebAPI11ResumePointV"},{"kind":"text","text":"?, "},{"kind":"externalParam","text":"durationMS"},{"kind":"text","text":": "},{"kind":"typeIdentifier","text":"Int","preciseIdentifier":"s:Si"},{"kind":"text","text":", "},{"kind":"externalParam","text":"isExplicit"},{"kind":"text","text":": "},{"kind":"typeIdentifier","text":"Bool","preciseIdentifier":"s:Sb"},{"kind":"text","text":", "},{"kind":"externalParam","text":"releaseDate"},{"kind":"text","text":": "},{"kind":"typeIdentifier","text":"Date","preciseIdentifier":"s:10Foundation4DateV"},{"kind":"text","text":"?, "},{"kind":"externalParam","text":"uri"},{"kind":"text","text":": "},{"kind":"typeIdentifier","text":"String","preciseIdentifier":"s:SS"},{"kind":"text","text":", "},{"kind":"externalParam","text":"id"},{"kind":"text","text":": "},{"kind":"typeIdentifier","text":"String","preciseIdentifier":"s:SS"},{"kind":"text","text":", "},{"kind":"externalParam","text":"images"},{"kind":"text","text":": ["},{"kind":"typeIdentifier","text":"SpotifyImage","preciseIdentifier":"s:13SpotifyWebAPI0A5ImageV"},{"kind":"text","text":"]?, "},{"kind":"externalParam","text":"availableMarkets"},{"kind":"text","text":": ["},{"kind":"typeIdentifier","text":"String","preciseIdentifier":"s:SS"},{"kind":"text","text":"]?, "},{"kind":"externalParam","text":"href"},{"kind":"text","text":": "},{"kind":"typeIdentifier","text":"URL","preciseIdentifier":"s:10Foundation3URLV"},{"kind":"text","text":", "},{"kind":"externalParam","text":"isPlayable"},{"kind":"text","text":": "},{"kind":"typeIdentifier","text":"Bool","preciseIdentifier":"s:Sb"},{"kind":"text","text":"?, "},{"kind":"externalParam","text":"externalURLs"},{"kind":"text","text":": ["},{"kind":"typeIdentifier","text":"String","preciseIdentifier":"s:SS"},{"kind":"text","text":" : "},{"kind":"typeIdentifier","text":"URL","preciseIdentifier":"s:10Foundation3URLV"},{"kind":"text","text":"]?, "},{"kind":"externalParam","text":"languages"},{"kind":"text","text":": ["},{"kind":"typeIdentifier","text":"String","preciseIdentifier":"s:SS"},{"kind":"text","text":"], "},{"kind":"externalParam","text":"restrictions"},{"kind":"text","text":": ["},{"kind":"typeIdentifier","text":"String","preciseIdentifier":"s:SS"},{"kind":"text","text":" : "},{"kind":"typeIdentifier","text":"String","preciseIdentifier":"s:SS"},{"kind":"text","text":"]?, "},{"kind":"externalParam","text":"releaseDatePrecision"},{"kind":"text","text":": "},{"kind":"typeIdentifier","text":"String","preciseIdentifier":"s:SS"},{"kind":"text","text":"?)"}],"abstract":[{"type":"text","text":"Creates a Spotify audiobook chapter."}],"identifier":"doc:\/\/SpotifyWebAPI\/documentation\/SpotifyWebAPI\/AudiobookChapter\/init(name:audiobook:chapterNumber:audioPreviewURL:description:htmlDescription:resumePoint:durationMS:isExplicit:releaseDate:uri:id:images:availableMarkets:href:isPlayable:externalURLs:languages:restrictions:releaseDatePrecision:)","kind":"symbol","type":"topic","url":"\/documentation\/spotifywebapi\/audiobookchapter\/init(name:audiobook:chapternumber:audiopreviewurl:description:htmldescription:resumepoint:durationms:isexplicit:releasedate:uri:id:images:availablemarkets:href:isplayable:externalurls:languages:restrictions:releasedateprecision:)"},"https://developer.spotify.com/documentation/web-api/#spotify-uris-and-ids":{"title":"Spotify URL","titleInlineContent":[{"type":"text","text":"Spotify"},{"type":"text","text":" "},{"type":"text","text":"URL"}],"type":"link","identifier":"https:\/\/developer.spotify.com\/documentation\/web-api\/#spotify-uris-and-ids","url":"https:\/\/developer.spotify.com\/documentation\/web-api\/#spotify-uris-and-ids"},"doc://SpotifyWebAPI/documentation/SpotifyWebAPI/ResumePoint":{"role":"symbol","title":"ResumePoint","fragments":[{"kind":"keyword","text":"struct"},{"kind":"text","text":" "},{"kind":"identifier","text":"ResumePoint"}],"abstract":[{"type":"text","text":"A Spotify resume point object. Represents the user’s most recent position"},{"type":"text","text":" "},{"type":"text","text":"in an episode or audiobook chapter."}],"identifier":"doc:\/\/SpotifyWebAPI\/documentation\/SpotifyWebAPI\/ResumePoint","kind":"symbol","type":"topic","navigatorTitle":[{"kind":"identifier","text":"ResumePoint"}],"url":"\/documentation\/spotifywebapi\/resumepoint"},"doc://SpotifyWebAPI/documentation/SpotifyWebAPI/AudiobookChapter/description":{"role":"symbol","title":"description","fragments":[{"kind":"keyword","text":"let"},{"kind":"text","text":" "},{"kind":"identifier","text":"description"},{"kind":"text","text":": "},{"kind":"typeIdentifier","text":"String","preciseIdentifier":"s:SS"}],"abstract":[{"type":"text","text":"A description of the chapter. See also "},{"type":"reference","isActive":true,"identifier":"doc:\/\/SpotifyWebAPI\/documentation\/SpotifyWebAPI\/AudiobookChapter\/htmlDescription"},{"type":"text","text":"."}],"identifier":"doc:\/\/SpotifyWebAPI\/documentation\/SpotifyWebAPI\/AudiobookChapter\/description","kind":"symbol","type":"topic","url":"\/documentation\/spotifywebapi\/audiobookchapter\/description"},"http://en.wikipedia.org/wiki/ISO_3166-1_alpha-2":{"title":"ISO 3166-1 alpha-2","titleInlineContent":[{"type":"text","text":"ISO 3166-1 alpha-2"}],"type":"link","identifier":"http:\/\/en.wikipedia.org\/wiki\/ISO_3166-1_alpha-2","url":"http:\/\/en.wikipedia.org\/wiki\/ISO_3166-1_alpha-2"},"doc://SpotifyWebAPI/documentation/SpotifyWebAPI/Audiobook":{"role":"symbol","title":"Audiobook","fragments":[{"kind":"keyword","text":"struct"},{"kind":"text","text":" "},{"kind":"identifier","text":"Audiobook"}],"abstract":[{"type":"text","text":"A Spotify audiobook."}],"identifier":"doc:\/\/SpotifyWebAPI\/documentation\/SpotifyWebAPI\/Audiobook","kind":"symbol","type":"topic","navigatorTitle":[{"kind":"identifier","text":"Audiobook"}],"url":"\/documentation\/spotifywebapi\/audiobook"},"doc://SpotifyWebAPI/documentation/SpotifyWebAPI/SpotifyAPI/getFromHref(_:responseType:)":{"conformance":{"constraints":[{"type":"codeVoice","code":"AuthorizationManager"},{"type":"text","text":" conforms to "},{"type":"codeVoice","code":"SpotifyAuthorizationManager"},{"type":"text","text":"."}],"availabilityPrefix":[{"type":"text","text":"Available when"}],"conformancePrefix":[{"type":"text","text":"Conforms when"}]},"role":"symbol","title":"getFromHref(_:responseType:)","fragments":[{"kind":"keyword","text":"func"},{"kind":"text","text":" "},{"kind":"identifier","text":"getFromHref"},{"kind":"text","text":"<"},{"kind":"genericParameter","text":"ResponseType"},{"kind":"text","text":">("},{"kind":"typeIdentifier","text":"URL","preciseIdentifier":"s:10Foundation3URLV"},{"kind":"text","text":", "},{"kind":"externalParam","text":"responseType"},{"kind":"text","text":": "},{"kind":"typeIdentifier","text":"ResponseType"},{"kind":"text","text":".Type) -> "},{"kind":"typeIdentifier","text":"AnyPublisher","preciseIdentifier":"s:7Combine12AnyPublisherV"},{"kind":"text","text":"<"},{"kind":"typeIdentifier","text":"ResponseType"},{"kind":"text","text":", "},{"kind":"typeIdentifier","text":"Error","preciseIdentifier":"s:s5ErrorP"},{"kind":"text","text":">"}],"abstract":[{"type":"text","text":"Retrieves the data linked to by an href and decodes it into "},{"type":"codeVoice","code":"responseType"},{"type":"text","text":"."}],"identifier":"doc:\/\/SpotifyWebAPI\/documentation\/SpotifyWebAPI\/SpotifyAPI\/getFromHref(_:responseType:)","kind":"symbol","type":"topic","url":"\/documentation\/spotifywebapi\/spotifyapi\/getfromhref(_:responsetype:)"},"doc://SpotifyWebAPI/documentation/SpotifyWebAPI/Scope/userReadPlaybackPosition":{"role":"symbol","title":"Scope.userReadPlaybackPosition","fragments":[{"kind":"keyword","text":"case"},{"kind":"text","text":" "},{"kind":"identifier","text":"userReadPlaybackPosition"}],"abstract":[{"type":"text","text":"Read access to a user’s playback position in an episodes."}],"identifier":"doc:\/\/SpotifyWebAPI\/documentation\/SpotifyWebAPI\/Scope\/userReadPlaybackPosition","kind":"symbol","type":"topic","url":"\/documentation\/spotifywebapi\/scope\/userreadplaybackposition"},"doc://SpotifyWebAPI/documentation/SpotifyWebAPI/Audiobook-Objects":{"role":"collectionGroup","title":"Audiobook Objects","abstract":[{"type":"text","text":"Objects that relate to the audiobook and audiobook chapter endpoints."}],"identifier":"doc:\/\/SpotifyWebAPI\/documentation\/SpotifyWebAPI\/Audiobook-Objects","kind":"article","type":"topic","url":"\/documentation\/spotifywebapi\/audiobook-objects"},"doc://SpotifyWebAPI/documentation/SpotifyWebAPI/AudiobookChapter/releaseDate":{"role":"symbol","title":"releaseDate","fragments":[{"kind":"keyword","text":"let"},{"kind":"text","text":" "},{"kind":"identifier","text":"releaseDate"},{"kind":"text","text":": "},{"kind":"typeIdentifier","text":"Date","preciseIdentifier":"s:10Foundation4DateV"},{"kind":"text","text":"?"}],"abstract":[{"type":"text","text":"The date the chapter was released."}],"identifier":"doc:\/\/SpotifyWebAPI\/documentation\/SpotifyWebAPI\/AudiobookChapter\/releaseDate","kind":"symbol","type":"topic","url":"\/documentation\/spotifywebapi\/audiobookchapter\/releasedate"},"doc://SpotifyWebAPI/documentation/SpotifyWebAPI/AudiobookChapter/releaseDatePrecision":{"role":"symbol","title":"releaseDatePrecision","fragments":[{"kind":"keyword","text":"let"},{"kind":"text","text":" "},{"kind":"identifier","text":"releaseDatePrecision"},{"kind":"text","text":": "},{"kind":"typeIdentifier","text":"String","preciseIdentifier":"s:SS"},{"kind":"text","text":"?"}],"abstract":[{"type":"text","text":"The precision with which "},{"type":"reference","isActive":true,"identifier":"doc:\/\/SpotifyWebAPI\/documentation\/SpotifyWebAPI\/AudiobookChapter\/releaseDate"},{"type":"text","text":" is known: “year”, “month”, or"},{"type":"text","text":" "},{"type":"text","text":"“day”."}],"identifier":"doc:\/\/SpotifyWebAPI\/documentation\/SpotifyWebAPI\/AudiobookChapter\/releaseDatePrecision","kind":"symbol","type":"topic","url":"\/documentation\/spotifywebapi\/audiobookchapter\/releasedateprecision"},"doc://SpotifyWebAPI/documentation/SpotifyWebAPI/AudiobookChapter":{"role":"symbol","title":"AudiobookChapter","fragments":[{"kind":"keyword","text":"struct"},{"kind":"text","text":" "},{"kind":"identifier","text":"AudiobookChapter"}],"abstract":[{"type":"text","text":"A Spotify audiobook chapter."}],"identifier":"doc:\/\/SpotifyWebAPI\/documentation\/SpotifyWebAPI\/AudiobookChapter","kind":"symbol","type":"topic","navigatorTitle":[{"kind":"identifier","text":"AudiobookChapter"}],"url":"\/documentation\/spotifywebapi\/audiobookchapter"},"doc://SpotifyWebAPI/documentation/SpotifyWebAPI/SpotifyImage":{"role":"symbol","title":"SpotifyImage","fragments":[{"kind":"keyword","text":"struct"},{"kind":"text","text":" "},{"kind":"identifier","text":"SpotifyImage"}],"abstract":[{"type":"text","text":"A Spotify image object."}],"identifier":"doc:\/\/SpotifyWebAPI\/documentation\/SpotifyWebAPI\/SpotifyImage","kind":"symbol","type":"topic","navigatorTitle":[{"kind":"identifier","text":"SpotifyImage"}],"url":"\/documentation\/spotifywebapi\/spotifyimage"},"doc://SpotifyWebAPI/documentation/SpotifyWebAPI":{"role":"collection","title":"SpotifyWebAPI","abstract":[{"type":"text","text":"A Swift library for the Spotify web API"}],"identifier":"doc:\/\/SpotifyWebAPI\/documentation\/SpotifyWebAPI","kind":"symbol","type":"topic","url":"\/documentation\/spotifywebapi"},"doc://SpotifyWebAPI/documentation/SpotifyWebAPI/AudiobookChapter/htmlDescription":{"role":"symbol","title":"htmlDescription","fragments":[{"kind":"keyword","text":"let"},{"kind":"text","text":" "},{"kind":"identifier","text":"htmlDescription"},{"kind":"text","text":": "},{"kind":"typeIdentifier","text":"String","preciseIdentifier":"s:SS"}],"abstract":[{"type":"text","text":"A description of the chapter which may contain HTML tags. See also"},{"type":"text","text":" "},{"type":"reference","isActive":true,"identifier":"doc:\/\/SpotifyWebAPI\/documentation\/SpotifyWebAPI\/AudiobookChapter\/description"},{"type":"text","text":"."}],"identifier":"doc:\/\/SpotifyWebAPI\/documentation\/SpotifyWebAPI\/AudiobookChapter\/htmlDescription","kind":"symbol","type":"topic","url":"\/documentation\/spotifywebapi\/audiobookchapter\/htmldescription"},"https://en.wikipedia.org/wiki/ISO_639":{"title":"ISO 639","titleInlineContent":[{"type":"text","text":"ISO 639"}],"type":"link","identifier":"https:\/\/en.wikipedia.org\/wiki\/ISO_639","url":"https:\/\/en.wikipedia.org\/wiki\/ISO_639"}}}